setup.py
hpc_package/__init__.py
hpc_package/hpc_codes.py
hpc_package.egg-info/PKG-INFO
hpc_package.egg-info/SOURCES.txt
hpc_package.egg-info/dependency_links.txt
hpc_package.egg-info/top_level.txt