Metadata-Version: 2.1
Name: hpc-package
Version: 1.0.0
Summary: hpc_codes
Author: geekaman22july
Author-email: geekaman22july@gmail.com
